[
	{
		"id": "Js06zStvMwY",
		"title": "liam search transcription test",
		"duration": 301,
		"uploader": "Liam Stream Archive",
		"uploaderUrl": "https://www.youtube.com/@LiamStreamArchive",
		"viewCount": 0,
		"tempAudioPath": null,
		"transcription": [
			{
				"from": "00:00:00.000",
				"to": "00:00:04.480",
				"text": "watch"
			},
			{
				"from": "00:00:04.480",
				"to": "00:00:09.860",
				"text": "look at how much"
			},
			{
				"from": "00:00:09.860",
				"to": "00:00:10.890",
				"text": "faster it is it's"
			},
			{
				"from": "00:00:10.890",
				"to": "00:00:13.440",
				"text": "like 0.6 faster i"
			},
			{
				"from": "00:00:13.440",
				"to": "00:00:14.350",
				"text": "practice this off"
			},
			{
				"from": "00:00:14.350",
				"to": "00:00:15.160",
				"text": "stream for two"
			},
			{
				"from": "00:00:15.160",
				"to": "00:00:15.840",
				"text": "hours that's"
			},
			{
				"from": "00:00:15.840",
				"to": "00:00:16.860",
				"text": "why are you putting"
			},
			{
				"from": "00:00:16.860",
				"to": "00:00:17.700",
				"text": "that in quotes i"
			},
			{
				"from": "00:00:17.700",
				"to": "00:00:18.400",
				"text": "act you know i"
			},
			{
				"from": "00:00:18.400",
				"to": "00:00:19.110",
				"text": "actually did"
			},
			{
				"from": "00:00:19.110",
				"to": "00:00:20.300",
				"text": "practice dark world"
			},
			{
				"from": "00:00:20.300",
				"to": "00:00:20.900",
				"text": "off stream for"
			},
			{
				"from": "00:00:20.900",
				"to": "00:00:22.210",
				"text": "two hours the other"
			},
			{
				"from": "00:00:22.210",
				"to": "00:00:22.890",
				"text": "day it was like"
			},
			{
				"from": "00:00:22.890",
				"to": "00:00:23.950",
				"text": "over a week ago now"
			},
			{
				"from": "00:00:23.950",
				"to": "00:00:24.880",
				"text": "but watch it's a"
			},
			{
				"from": "00:00:24.880",
				"to": "00:00:26.040",
				"text": "four second whoops"
			},
			{
				"from": "00:00:26.040",
				"to": "00:00:26.480",
				"text": "four"
			},
			{
				"from": "00:00:26.480",
				"to": "00:00:27.560",
				"text": "second time saved"
			},
			{
				"from": "00:00:27.560",
				"to": "00:00:28.960",
				"text": "dude that was crazy"
			},
			{
				"from": "00:00:28.960",
				"to": "00:00:29.780",
				"text": "you think so"
			},
			{
				"from": "00:00:29.780",
				"to": "00:00:32.760",
				"text": "actually watch"
			},
			{
				"from": "00:00:32.760",
				"to": "00:00:36.800",
				"text": "by the way"
			},
			{
				"from": "00:00:36.800",
				"to": "00:00:41.560",
				"text": "i think i'm finally"
			},
			{
				"from": "00:00:41.560",
				"to": "00:00:44.970",
				"text": "ready to lock in"
			},
			{
				"from": "00:00:44.970",
				"to": "00:00:47.330",
				"text": "but i don't expect"
			},
			{
				"from": "00:00:47.330",
				"to": "00:00:49.220",
				"text": "you to believe me"
			},
			{
				"from": "00:00:51.220",
				"to": "00:00:54.680",
				"text": "whoops i i probably"
			},
			{
				"from": "00:00:54.680",
				"to": "00:00:56.270",
				"text": "will stream"
			},
			{
				"from": "00:00:56.270",
				"to": "00:00:57.600",
				"text": "tomorrow"
			},
			{
				"from": "00:00:57.600",
				"to": "00:00:59.340",
				"text": "and once i do two"
			},
			{
				"from": "00:00:59.340",
				"to": "00:01:00.810",
				"text": "days in a row i"
			},
			{
				"from": "00:01:00.810",
				"to": "00:01:01.910",
				"text": "think i'll be"
			},
			{
				"from": "00:01:01.910",
				"to": "00:01:02.620",
				"text": "unstoppable"
			},
			{
				"from": "00:01:02.620",
				"to": "00:01:06.040",
				"text": "but i think"
			},
			{
				"from": "00:01:06.040",
				"to": "00:01:09.120",
				"text": "this is also not a"
			},
			{
				"from": "00:01:09.120",
				"to": "00:01:09.910",
				"text": "lie i'm thinking"
			},
			{
				"from": "00:01:09.910",
				"to": "00:01:11.360",
				"text": "about visiting my"
			},
			{
				"from": "00:01:11.360",
				"to": "00:01:12.840",
				"text": "uh sister"
			},
			{
				"from": "00:01:12.840",
				"to": "00:01:15.000",
				"text": "maybe for the"
			},
			{
				"from": "00:01:15.000",
				"to": "00:01:16.360",
				"text": "holidays"
			},
			{
				"from": "00:01:16.360",
				"to": "00:01:18.010",
				"text": "what do you mean"
			},
			{
				"from": "00:01:18.010",
				"to": "00:01:19.390",
				"text": "here we go i'm"
			},
			{
				"from": "00:01:19.390",
				"to": "00:01:21.040",
				"text": "being serious i"
			},
			{
				"from": "00:01:21.040",
				"to": "00:01:22.900",
				"text": "haven't seen her"
			},
			{
				"from": "00:01:22.900",
				"to": "00:01:24.730",
				"text": "since 20 2020 i"
			},
			{
				"from": "00:01:24.730",
				"to": "00:01:25.400",
				"text": "think"
			},
			{
				"from": "00:01:25.400",
				"to": "00:01:27.130",
				"text": "she's probably busy"
			},
			{
				"from": "00:01:27.130",
				"to": "00:01:28.540",
				"text": "she's not busy at"
			},
			{
				"from": "00:01:28.540",
				"to": "00:01:29.510",
				"text": "all you literally"
			},
			{
				"from": "00:01:29.510",
				"to": "00:01:30.080",
				"text": "said you're gonna"
			},
			{
				"from": "00:01:30.080",
				"to": "00:01:30.860",
				"text": "stream every day of"
			},
			{
				"from": "00:01:30.860",
				"to": "00:01:31.620",
				"text": "november and stream"
			},
			{
				"from": "00:01:31.620",
				"to": "00:01:32.150",
				"text": "like twice the"
			},
			{
				"from": "00:01:32.150",
				"to": "00:01:32.980",
				"text": "whole month okay"
			},
			{
				"from": "00:01:32.980",
				"to": "00:01:33.390",
				"text": "just so you know"
			},
			{
				"from": "00:01:33.390",
				"to": "00:01:33.970",
				"text": "when i said i was"
			},
			{
				"from": "00:01:33.970",
				"to": "00:01:34.520",
				"text": "gonna stream"
			},
			{
				"from": "00:01:34.520",
				"to": "00:01:35.740",
				"text": "every day of november"
			},
			{
				"from": "00:01:35.740",
				"to": "00:01:36.260",
				"text": "i like in my"
			},
			{
				"from": "00:01:36.260",
				"to": "00:01:37.250",
				"text": "opinion it was very"
			},
			{
				"from": "00:01:37.250",
				"to": "00:01:38.270",
				"text": "obvious that i wasn't"
			},
			{
				"from": "00:01:38.270",
				"to": "00:01:39.000",
				"text": "being serious"
			},
			{
				"from": "00:01:39.000",
				"to": "00:01:39.800",
				"text": "did you really"
			},
			{
				"from": "00:01:39.800",
				"to": "00:01:40.770",
				"text": "believe it do you"
			},
			{
				"from": "00:01:40.770",
				"to": "00:01:41.500",
				"text": "just believe"
			},
			{
				"from": "00:01:41.500",
				"to": "00:01:42.150",
				"text": "everything"
			},
			{
				"from": "00:01:42.150",
				"to": "00:01:43.250",
				"text": "everybody says even"
			},
			{
				"from": "00:01:43.250",
				"to": "00:01:44.060",
				"text": "if it's in a"
			},
			{
				"from": "00:01:44.060",
				"to": "00:01:45.230",
				"text": "clearly joking tone"
			},
			{
				"from": "00:01:45.230",
				"to": "00:01:46.520",
				"text": "i can't breathe"
			},
			{
				"from": "00:01:46.520",
				"to": "00:01:47.700",
				"text": "right now i feel"
			},
			{
				"from": "00:01:47.700",
				"to": "00:01:48.560",
				"text": "like i'm out of"
			},
			{
				"from": "00:01:48.560",
				"to": "00:01:49.040",
				"text": "breath"
			},
			{
				"from": "00:01:49.040",
				"to": "00:01:52.600",
				"text": "thought you said"
			},
			{
				"from": "00:01:52.600",
				"to": "00:01:56.180",
				"text": "she had a wrinkle"
			},
			{
				"from": "00:01:56.180",
				"to": "00:01:56.890",
				"text": "yeah she is very"
			},
			{
				"from": "00:01:56.890",
				"to": "00:01:57.740",
				"text": "old she's gonna be"
			},
			{
				"from": "00:01:57.740",
				"to": "00:01:58.740",
				"text": "very gross to look"
			},
			{
				"from": "00:01:58.740",
				"to": "00:01:59.060",
				"text": "at"
			},
			{
				"from": "00:01:59.060",
				"to": "00:02:00.720",
				"text": "that you cory cubed"
			},
			{
				"from": "00:02:00.720",
				"to": "00:02:01.860",
				"text": "for the seven"
			},
			{
				"from": "00:02:01.860",
				"to": "00:02:02.540",
				"text": "months"
			},
			{
				"from": "00:02:02.540",
				"to": "00:02:07.380",
				"text": "you have jowls i do"
			},
			{
				"from": "00:02:07.380",
				"to": "00:02:08.340",
				"text": "not have jowls"
			},
			{
				"from": "00:02:08.340",
				"to": "00:02:13.120",
				"text": "no no stream november"
			},
			{
				"from": "00:02:13.120",
				"to": "00:02:14.900",
				"text": "was a play on words"
			},
			{
				"from": "00:02:14.900",
				"to": "00:02:15.810",
				"text": "it was a play it"
			},
			{
				"from": "00:02:15.810",
				"to": "00:02:18.080",
				"text": "was me poking uh"
			},
			{
				"from": "00:02:18.080",
				"to": "00:02:19.520",
				"text": "fun at the"
			},
			{
				"from": "00:02:19.520",
				"to": "00:02:21.440",
				"text": "tradition of no nut"
			},
			{
				"from": "00:02:21.440",
				"to": "00:02:22.870",
				"text": "november do you"
			},
			{
				"from": "00:02:22.870",
				"to": "00:02:23.800",
				"text": "understand now"
			},
			{
				"from": "00:02:23.800",
				"to": "00:02:31.560",
				"text": "come on i think you"
			},
			{
				"from": "00:02:31.560",
				"to": "00:02:32.070",
				"text": "lamp slide for the"
			},
			{
				"from": "00:02:32.070",
				"to": "00:02:32.340",
				"text": "33"
			},
			{
				"from": "00:02:32.340",
				"to": "00:02:33.620",
				"text": "man you need to"
			},
			{
				"from": "00:02:33.620",
				"to": "00:02:35.240",
				"text": "stop taking photo"
			},
			{
				"from": "00:02:35.240",
				"to": "00:02:37.330",
				"text": "picture poof thank"
			},
			{
				"from": "00:02:37.330",
				"to": "00:02:38.890",
				"text": "you proto mans for"
			},
			{
				"from": "00:02:38.890",
				"to": "00:02:39.700",
				"text": "the good luck moon"
			},
			{
				"from": "00:02:39.700",
				"to": "00:02:40.590",
				"text": "are you sick my"
			},
			{
				"from": "00:02:40.590",
				"to": "00:02:41.820",
				"text": "voice is like super"
			},
			{
				"from": "00:02:41.820",
				"to": "00:02:43.030",
				"text": "strained because i"
			},
			{
				"from": "00:02:43.030",
				"to": "00:02:44.030",
				"text": "was talking all"
			},
			{
				"from": "00:02:44.030",
				"to": "00:02:45.180",
				"text": "night last night"
			},
			{
				"from": "00:02:45.180",
				"to": "00:02:48.390",
				"text": "i was at sort of a"
			},
			{
				"from": "00:02:48.390",
				"to": "00:02:51.460",
				"text": "social excursion"
			},
			{
				"from": "00:02:51.460",
				"to": "00:02:52.880",
				"text": "it was not to"
			},
			{
				"from": "00:02:52.880",
				"to": "00:02:54.950",
				"text": "myself it was to"
			},
			{
				"from": "00:02:54.950",
				"to": "00:02:56.430",
				"text": "many people"
			},
			{
				"from": "00:02:56.430",
				"to": "00:02:58.220",
				"text": "including women"
			},
			{
				"from": "00:02:58.220",
				"to": "00:03:02.070",
				"text": "to who yourself in"
			},
			{
				"from": "00:03:02.070",
				"to": "00:03:04.700",
				"text": "the mirror that's"
			},
			{
				"from": "00:03:04.700",
				"to": "00:03:05.420",
				"text": "hilarious anybody"
			},
			{
				"from": "00:03:05.420",
				"to": "00:03:06.140",
				"text": "got an original"
			},
			{
				"from": "00:03:06.140",
				"to": "00:03:06.540",
				"text": "joke"
			},
			{
				"from": "00:03:06.540",
				"to": "00:03:09.780",
				"text": "poor women"
			},
			{
				"from": "00:03:09.780",
				"to": "00:03:19.280",
				"text": "one of these days i'm"
			},
			{
				"from": "00:03:19.280",
				"to": "00:03:20.380",
				"text": "going to"
			},
			{
				"from": "00:03:20.380",
				"to": "00:03:25.160",
				"text": "film like an entire"
			},
			{
				"from": "00:03:25.160",
				"to": "00:03:29.450",
				"text": "like a pov of me at"
			},
			{
				"from": "00:03:29.450",
				"to": "00:03:30.440",
				"text": "one of the parties"
			},
			{
				"from": "00:03:30.440",
				"to": "00:03:31.060",
				"text": "that i go to"
			},
			{
				"from": "00:03:31.060",
				"to": "00:03:31.770",
				"text": "maybe with the"
			},
			{
				"from": "00:03:31.770",
				"to": "00:03:32.620",
				"text": "glasses the meta"
			},
			{
				"from": "00:03:32.620",
				"to": "00:03:33.060",
				"text": "glasses"
			},
			{
				"from": "00:03:33.060",
				"to": "00:03:35.740",
				"text": "and i just want you"
			},
			{
				"from": "00:03:35.740",
				"to": "00:03:37.530",
				"text": "guys to see how"
			},
			{
				"from": "00:03:37.530",
				"to": "00:03:38.780",
				"text": "normal i am"
			},
			{
				"from": "00:03:38.780",
				"to": "00:03:41.020",
				"text": "dude"
			},
			{
				"from": "00:03:41.020",
				"to": "00:03:43.130",
				"text": "you're so fucking"
			},
			{
				"from": "00:03:43.130",
				"to": "00:03:44.800",
				"text": "weird dude blood"
			},
			{
				"from": "00:03:44.800",
				"to": "00:03:46.140",
				"text": "they have a light"
			},
			{
				"from": "00:03:46.140",
				"to": "00:03:47.120",
				"text": "on so you know they're"
			},
			{
				"from": "00:03:47.120",
				"to": "00:03:47.880",
				"text": "recording that's"
			},
			{
				"from": "00:03:47.880",
				"to": "00:03:49.000",
				"text": "the whole point how"
			},
			{
				"from": "00:03:49.000",
				"to": "00:03:49.680",
				"text": "long until they"
			},
			{
				"from": "00:03:49.680",
				"to": "00:03:50.900",
				"text": "make glasses where"
			},
			{
				"from": "00:03:50.900",
				"to": "00:03:51.680",
				"text": "you can hide the"
			},
			{
				"from": "00:03:51.680",
				"to": "00:03:52.780",
				"text": "light or not have a"
			},
			{
				"from": "00:03:52.780",
				"to": "00:03:52.960",
				"text": "light"
			},
			{
				"from": "00:03:52.960",
				"to": "00:04:00.040",
				"text": "is that actually"
			},
			{
				"from": "00:04:00.040",
				"to": "00:04:05.680",
				"text": "illegal"
			},
			{
				"from": "00:04:05.680",
				"to": "00:04:07.360",
				"text": "now watch"
			},
			{
				"from": "00:04:07.360",
				"to": "00:04:10.300",
				"text": "ah"
			},
			{
				"from": "00:04:10.300",
				"to": "00:04:13.530",
				"text": "i think it's"
			},
			{
				"from": "00:04:13.530",
				"to": "00:04:13.960",
				"text": "illegal"
			},
			{
				"from": "00:04:13.960",
				"to": "00:04:16.200",
				"text": "cut a little circle"
			},
			{
				"from": "00:04:16.200",
				"to": "00:04:17.340",
				"text": "hole in your jacket"
			},
			{
				"from": "00:04:17.340",
				"to": "00:04:18.280",
				"text": "and have your phone"
			},
			{
				"from": "00:04:18.280",
				"to": "00:04:19.000",
				"text": "camera record"
			},
			{
				"from": "00:04:19.000",
				"to": "00:04:19.700",
				"text": "through it"
			},
			{
				"from": "00:04:19.700",
				"to": "00:04:20.410",
				"text": "blood i'm not"
			},
			{
				"from": "00:04:20.410",
				"to": "00:04:21.450",
				"text": "looking for ways to"
			},
			{
				"from": "00:04:21.450",
				"to": "00:04:22.420",
				"text": "secretly record"
			},
			{
				"from": "00:04:22.420",
				"to": "00:04:22.740",
				"text": "people"
			},
			{
				"from": "00:04:22.740",
				"to": "00:04:23.300",
				"text": "i'm good"
			},
			{
				"from": "00:04:23.300",
				"to": "00:04:24.140",
				"text": "it's just very"
			},
			{
				"from": "00:04:24.140",
				"to": "00:04:25.000",
				"text": "creepy i'm not a"
			},
			{
				"from": "00:04:25.000",
				"to": "00:04:25.900",
				"text": "creep in real life"
			},
			{
				"from": "00:04:25.900",
				"to": "00:04:26.910",
				"text": "are you proud of"
			},
			{
				"from": "00:04:26.910",
				"to": "00:04:27.470",
				"text": "man's for the gift"
			},
			{
				"from": "00:04:27.470",
				"to": "00:04:29.740",
				"text": "that's up to ben rl"
			},
			{
				"from": "00:04:29.740",
				"to": "00:04:30.420",
				"text": "buddy"
			},
			{
				"from": "00:04:30.420",
				"to": "00:04:33.940",
				"text": "you know in some"
			},
			{
				"from": "00:04:33.940",
				"to": "00:04:34.720",
				"text": "countries they"
			},
			{
				"from": "00:04:34.720",
				"to": "00:04:35.300",
				"text": "force the cameras"
			},
			{
				"from": "00:04:35.300",
				"to": "00:04:35.990",
				"text": "to have an audible"
			},
			{
				"from": "00:04:35.990",
				"to": "00:04:36.640",
				"text": "shutter noise"
			},
			{
				"from": "00:04:36.640",
				"to": "00:04:37.550",
				"text": "yeah i think that"
			},
			{
				"from": "00:04:37.550",
				"to": "00:04:38.500",
				"text": "is in japan right"
			},
			{
				"from": "00:04:38.500",
				"to": "00:04:40.390",
				"text": "how come japan is"
			},
			{
				"from": "00:04:40.390",
				"to": "00:04:41.540",
				"text": "full of creeps is"
			},
			{
				"from": "00:04:41.540",
				"to": "00:04:42.200",
				"text": "it just like the"
			},
			{
				"from": "00:04:42.200",
				"to": "00:04:42.580",
				"text": "culture"
			},
			{
				"from": "00:04:42.580",
				"to": "00:04:51.170",
				"text": "oh no who's racist"
			},
			{
				"from": "00:04:51.170",
				"to": "00:04:52.660",
				"text": "yes it's racist to"
			},
			{
				"from": "00:04:52.660",
				"to": "00:04:53.390",
				"text": "say that one"
			},
			{
				"from": "00:04:53.390",
				"to": "00:04:54.490",
				"text": "country is full of"
			},
			{
				"from": "00:04:54.490",
				"to": "00:04:55.300",
				"text": "creeps you're right"
			},
			{
				"from": "00:04:55.300",
				"to": "00:04:57.860",
				"text": "that is the most"
			},
			{
				"from": "00:04:57.860",
				"to": "00:04:59.420",
				"text": "racist shit"
			}
		]
	}
]